amlensing/__init__.py
amlensing/amlensing.cfg
amlensing/approx.py
amlensing/astrometry.py
amlensing/calculation.py
amlensing/cmdline.py
amlensing/filter_bgs.py
amlensing/filter_lens.py
amlensing/filter_pair.py
amlensing/find_closest.py
amlensing/main.py
amlensing/mass.py
amlensing/microlensing.py
amlensing/raw_data.py
amlensing/utils/__init__.py
amlensing/utils/crossmatch.py
amlensing/utils/query.py
amlensing-0.1.2.dist-info/LICENSE
amlensing-0.1.2.dist-info/METADATA
amlensing-0.1.2.dist-info/WHEEL
amlensing-0.1.2.dist-info/entry_points.txt
amlensing-0.1.2.dist-info/top_level.txt
amlensing-0.1.2.dist-info/RECORD
