Metadata-Version: 2.1
Name: amlensing
Version: 0.1.2
Summary: Astrometric microlensing prediction with Gaia sources
Author-email: Lu Xu <oliver_lew@outlook.com>
License: GPL v3.0
Project-URL: homepage, https://github.com/xlucn/GAML
Keywords: astronomy,gravitational lensing,gaia,astrometry
Classifier: Programming Language :: Python :: 3
License-File: LICENSE
Requires-Dist: numpy >=1.19.5
Requires-Dist: scipy
Requires-Dist: matplotlib >=3.3.3
Requires-Dist: astropy >=4.2
Requires-Dist: astroquery >=0.4.1
Requires-Dist: pyvo >=1.1
Provides-Extra: progressbar
Requires-Dist: tqdm ; extra == 'progressbar'
